pdf2md_ocr/__init__.py
pdf2md_ocr/cli.py
pdf2md_ocr-1.0.1.dist-info/METADATA
pdf2md_ocr-1.0.1.dist-info/WHEEL
pdf2md_ocr-1.0.1.dist-info/entry_points.txt
pdf2md_ocr-1.0.1.dist-info/licenses/LICENSE
pdf2md_ocr-1.0.1.dist-info/RECORD
