Metadata-Version: 2.4
Name: pdf2md-ocr
Version: 1.0.1
Summary: Simple CLI tool to convert PDFs to Markdown using Marker AI
Project-URL: Homepage, https://github.com/carloscasalar/pdf2md-ocr
Project-URL: Repository, https://github.com/carloscasalar/pdf2md-ocr
Project-URL: Issues, https://github.com/carloscasalar/pdf2md-ocr/issues
Author-email: Carlos Castillo <castillo.st+pdf2md-ocr@gmail.com>
License: GPL-3.0-or-later
License-File: LICENSE
Keywords: cli,conversion,markdown,ocr,pdf
Classifier: Development Status :: 3 - Alpha
Classifier: Intended Audience :: Developers
Classifier: License :: OSI Approved :: GNU General Public License v3 or later (GPLv3+)
Classifier: Programming Language :: Python :: 3
Classifier: Programming Language :: Python :: 3.10
Classifier: Programming Language :: Python :: 3.11
Classifier: Programming Language :: Python :: 3.12
Classifier: Programming Language :: Python :: 3.13
Classifier: Topic :: Text Processing :: Markup :: Markdown
Requires-Python: >=3.10
Requires-Dist: click
Requires-Dist: marker-pdf==1.10.1
Requires-Dist: pypdf==6.6.0
Requires-Dist: rich
Provides-Extra: dev
Requires-Dist: pytest>=8.0.0; extra == 'dev'
